sizer/__init__.py
sizer/__main__.py
sizer/sizer.py
sizer-1.0.0.dist-info/METADATA
sizer-1.0.0.dist-info/WHEEL
sizer-1.0.0.dist-info/top_level.txt
sizer-1.0.0.dist-info/RECORD
