Metadata-Version: 2.1
Name: sizer
Version: 1.0.0
Summary: A simple Python script for iterating recursively over a directory and returning all of the files sorted by size
Author-email: Georgi Petrov <petrov.d.george@gmail.com>
Classifier: Programming Language :: Python :: 3
Classifier: License :: OSI Approved :: MIT License
Classifier: Operating System :: OS Independent
Requires-Python: >=3.8
Requires-Dist: requests
Requires-Dist: importlib-metadata ; python_version > "3.8"
